moneycontrol/__init__.py
moneycontrol/moneycontrol_api.py
moneycontrol_api-1.1.4.dist-info/LICENSE
moneycontrol_api-1.1.4.dist-info/METADATA
moneycontrol_api-1.1.4.dist-info/WHEEL
moneycontrol_api-1.1.4.dist-info/top_level.txt
moneycontrol_api-1.1.4.dist-info/RECORD
