Metadata-Version: 2.1
Name: moneycontrol_api
Version: 1.1.4
Summary: Moneycontrol API is a python library to get news data from moneycontrol.com in JSON format.
Author-email: Arabian Coconut <x48cl9zm@duck.com>
Project-URL: Homepage, https://github.com/ArabianCoconut/Moneycontrol-api
Project-URL: Live Demo, https://mc-api-j0rn.onrender.com
Keywords: moneycontrol api,moneycontrol
Classifier: Programming Language :: Python :: 3
Classifier: License :: OSI Approved :: GNU General Public License v3 (GPLv3)
Classifier: Operating System :: OS Independent
Requires-Python: >=3.11
License-File: LICENSE
